pkg/__init__.py
resume_nicolas_karolak-0.1.0.dist-info/WHEEL
resume_nicolas_karolak-0.1.0.dist-info/METADATA
resume_nicolas_karolak-0.1.0.dist-info/RECORD
